scheduler/__init__.py
scheduler/__main__.py
scheduler/games_generation.py
scheduler/schedule_generation.py
tournament_scheduler-0.1.3.dist-info/LICENSE
tournament_scheduler-0.1.3.dist-info/METADATA
tournament_scheduler-0.1.3.dist-info/WHEEL
tournament_scheduler-0.1.3.dist-info/dependency_links.txt
tournament_scheduler-0.1.3.dist-info/entry_points.txt
tournament_scheduler-0.1.3.dist-info/top_level.txt
tournament_scheduler-0.1.3.dist-info/RECORD
