Metadata-Version: 2.1
Name: tournament-scheduler
Version: 0.1.3
Summary: A command-line tool to generate a tournament schedule
Home-page: https://github.com/fdebellabre/tournament-scheduler
Author: Foucauld de Bellabre
Author-email: fdebellabre@gmail.com
License: LICENSE.txt
Keywords: tournament,league,schedule,timetable
Classifier: License :: OSI Approved :: GNU General Public License v3 (GPLv3)
Classifier: Programming Language :: Python :: 3
License-File: LICENSE
Requires-Dist: numpy ==1.*
Requires-Dist: pandas ==1.*
Requires-Dist: click ==7.*
